{
  "allow": [
    {
      "id": "UCS5Oz6CHmeoF7vSad0qqXfw",
      "display": "DanTDM"
    },
    {
      "id": "UCa94pyq0HNK8qAFUBJiVAeA",
      "display": "DanTDM Live"
    },
    {
      "id": "UCmr0m5RQoEDXQY3hFBIEK3w",
      "display": "MoreTDM"
    },
    {
      "id": "UCKYb5XBe-5OSEgLijLSoDtw",
      "display": "UnspeakableGaming"
    },
    {
      "id": "UCwIWAbIeu0xI0ReKWOcw3eg",
      "display": "Unspeakable"
    },
    {
      "id": "UC1n_yB_W-FZCbwajZPcs8Jw",
      "display": "UnspeakablePlays"
    },
    {
      "id": "UC0rDDvHM7u_7aWgAojSXl1Q",
      "display": "DaveHax"
    },
    {
      "id": "UChd1FPXykD4pust3ljzq6hQ",
      "display": "Thinknoodles"
    },
    {
      "id": "UCX6OQ3DkcsbYNE6H8uQQuVA",
      "display": "MrBeast"
    },
    {
      "id": "UCIPPMRA040LQr5QPyJEbmXA",
      "display": "MrBeast Gaming"
    },
    {
      "id": "UCY1kMZp36IQSyNx_9h4mpCg",
      "display": "Mark Rober"
    },
    {
      "id": "UC2C_jShtL725hvbm1arSV9w",
      "display": "CGP Grey"
    },
    {
      "id": "UCFKDEp9si4RmHFWJW1vYsMA",
      "display": "EthosLab"
    },
    {
      "id": "UCRlEFn0L2G_DktbyvN0AZ5A",
      "display": "WadZee"
    },
    {
      "id": "UCiYcA0gJzg855iSKMrX3oHg",
      "display": "CoryxKenshin"
    },
    {
      "id": "UCqmugCqELzhIMNYnsjScXXw",
      "display": "Vsauce2"
    },
    {
      "id": "UC6nSFpj9HTCZ5t-N3Rm3-HA",
      "display": "Vsauce"
    },
    {
      "id": "UCIabPXjvT5BVTxRDPCBBOOQ",
      "display": "Dani"
    },
    {
      "id": "UCj5i58mCkAREDqFWlhaQbOw",
      "display": "stampylonghead"
    },
    {
      "id": "UC70Dib4MvFfT1tU6MqeyHpQ",
      "display": "Preston"
    },
    {
      "id": "UCJZam2u1G0syq3kyqrCXrNw",
      "display": "PrestonPlayz"
    },
    {
      "id": "UCmr_vYKbp98f6kdRoer0iVw",
      "display": "PrestonGamez"
    },
    {
      "id": "UCpGdL9Sn3Q5YWUH2DVUW1Ug",
      "display": "PopularMMOs"
    }
  ]
}